[
  {
    "m": "2024-06",
    "date": "2024-06-15",
    "rate": null,
    "src": "no archive"
  },
  {
    "m": "2024-07",
    "date": "2024-07-16",
    "rate": 5.781,
    "src": "NerdWallet (Wayback)"
  },
  {
    "m": "2024-08",
    "date": "2024-08-15",
    "rate": null,
    "src": "no archive"
  },
  {
    "m": "2024-09",
    "date": "2024-09-17",
    "rate": 4.9,
    "src": "NerdWallet (Wayback)"
  },
  {
    "m": "2024-10",
    "date": "2024-10-06",
    "rate": 5.44,
    "src": "NerdWallet (Wayback)"
  },
  {
    "m": "2024-11",
    "date": "2024-11-13",
    "rate": 6.096,
    "src": "NerdWallet (Wayback)"
  },
  {
    "m": "2024-12",
    "date": "2024-12-17",
    "rate": 5.784,
    "src": "NerdWallet (Wayback)"
  },
  {
    "m": "2025-01",
    "date": "2025-01-19",
    "rate": 5.979,
    "src": "NerdWallet (Wayback)"
  },
  {
    "m": "2025-02",
    "date": "2025-02-15",
    "rate": null,
    "src": "no archive"
  },
  {
    "m": "2025-03",
    "date": "2025-03-06",
    "rate": 5.639,
    "src": "NerdWallet (Wayback)"
  },
  {
    "m": "2025-04",
    "date": "2025-04-24",
    "rate": 6.121,
    "src": "NerdWallet (Wayback)"
  },
  {
    "m": "2025-05",
    "date": "2025-05-21",
    "rate": 6.114,
    "src": "NerdWallet (Wayback)"
  },
  {
    "m": "2025-06",
    "date": "2025-06-15",
    "rate": null,
    "src": "no archive"
  },
  {
    "m": "2025-07",
    "date": "2025-07-15",
    "rate": null,
    "src": "no archive"
  },
  {
    "m": "2025-08",
    "date": "2025-08-13",
    "rate": 5.727,
    "src": "NerdWallet (Wayback)"
  },
  {
    "m": "2025-09",
    "date": "2025-09-17",
    "rate": 5.52,
    "src": "NerdWallet (Wayback)"
  },
  {
    "m": "2025-10",
    "date": "2025-10-11",
    "rate": 5.82,
    "src": "NerdWallet (Wayback)"
  },
  {
    "m": "2025-11",
    "date": "2025-11-15",
    "rate": 5.71,
    "src": "NerdWallet (Wayback)"
  },
  {
    "m": "2025-12",
    "date": "2025-12-07",
    "rate": 5.6,
    "src": "NerdWallet (Wayback)"
  },
  {
    "m": "2026-01",
    "date": "2026-01-13",
    "rate": 5.43,
    "src": "NerdWallet (Wayback)"
  },
  {
    "m": "2026-02",
    "date": "2026-02-13",
    "rate": 5.31,
    "src": "NerdWallet (Wayback)"
  },
  {
    "m": "2026-03",
    "date": "2026-03-15",
    "rate": null,
    "src": "no archive"
  },
  {
    "m": "2026-04",
    "date": "2026-04-15",
    "rate": null,
    "src": "no archive"
  },
  {
    "m": "2026-05",
    "date": "2026-05-15",
    "rate": null,
    "src": "no archive"
  },
  {
    "m": "2026-06",
    "date": "2026-06-30",
    "rate": 5.78,
    "src": "NerdWallet"
  },
  {
    "m": "2026-07",
    "date": "2026-07-07",
    "rate": 5.96,
    "src": "NerdWallet"
  }
]